Metadata-Version: 2.1
Name: mpl-styles
Version: 1.0.0
Summary: Add stylesheets to matplotlib
Home-page: UNKNOWN
Author: Sebastian Hurtado
License: UNKNOWN
Keywords: matplotlib-styles,python
Platform: UNKNOWN
